{"type": "Feature", "id": 12517520, "geometry": {"type": "Point", "coordinates": [-11.1753, 7.895]}, "properties": {"woe:id": 12517520, "woe:parent_id": 1513826, "woe:name": "Kenema Airport", "woe:placetype": 14, "woe:placetype_name": "Airport", "woe:lang": "ENG", "iso:country": "SL", "meta:provider": ["geoplanet:7.3.1", "geoplanet:7.3.2", "geoplanet:7.4.0", "geoplanet:7.4.1", "geoplanet:7.5.1", "geoplanet:7.5.2", "geoplanet:7.6.0", "geoplanet:7.8.1", "geoplanet:7.9.0", "geoplanet:7.10.0", "geoplanet:8.0.0", "woeplanet:8.0.0"], "meta:indexed": "2020-08-20T20:49:15.579042", "woe:alias_ENG_V": ["KEN Airport", "KEN"], "meta:updated": "2020-10-14T11:09:06.732956", "woe:hierarchy": {"continent": 24865670, "country": 23424946, "town": 0, "planet": 1, "county": 0, "suburb": 0, "state": 2347000, "region": 0, "localadmin": 0}, "woe:timezone_id": 28350701, "woe:hash": "ec2hctnrswsm", "woe:centroid": [-11.1753, 7.895], "geom:latitude": 7.895, "geom:longitude": -11.1753, "geom:hash": "ec2hctnrswsm", "woe:latitude": 7.895, "geom:centroid": [-11.1753, 7.895], "woe:longitude": -11.1753, "woe:repo": "woeplanet-airport-sl", "geom:area": 0.0, "woe:scale": 19}}